nsz/BlockCompressor.py
nsz/BlockDecompressorReader.py
nsz/ExtractTitlekeys.py
nsz/FileExistingChecks.py
nsz/Header.py
nsz/IndependentNczDecompressor.py
nsz/NszDecompressor.py
nsz/ParseArguments.py
nsz/PathTools.py
nsz/SectionFs.py
nsz/SolidCompressor.py
nsz/ThreadSafeCounterManager.py
nsz/ThreadSafeCounterSharedMemory.py
nsz/__init__.py
nsz/undupe.py
nsz/Fs/BaseFs.py
nsz/Fs/Bktr.py
nsz/Fs/Cnmt.py
nsz/Fs/File.py
nsz/Fs/Hfs0.py
nsz/Fs/Ivfc.py
nsz/Fs/Nacp.py
nsz/Fs/Nca.py
nsz/Fs/Nsp.py
nsz/Fs/Pfs0.py
nsz/Fs/Rom.py
nsz/Fs/Ticket.py
nsz/Fs/Type.py
nsz/Fs/Xci.py
nsz/Fs/__init__.py
nsz/dist/__init__/cv2/__init__.py
nsz/dist/__init__/cv2/config-3.py
nsz/dist/__init__/cv2/config.py
nsz/dist/__init__/cv2/load_config_py2.py
nsz/dist/__init__/cv2/load_config_py3.py
nsz/dist/__init__/cv2/version.py
nsz/dist/__init__/cv2/data/__init__.py
nsz/dist/__init__/cv2/gapi/__init__.py
nsz/dist/__init__/cv2/mat_wrapper/__init__.py
nsz/dist/__init__/cv2/misc/__init__.py
nsz/dist/__init__/cv2/misc/version.py
nsz/dist/__init__/cv2/utils/__init__.py
nsz/dist/__init__/kivy_install/modules/__init__.py
nsz/dist/__init__/kivy_install/modules/_webdebugger.py
nsz/dist/__init__/kivy_install/modules/console.py
nsz/dist/__init__/kivy_install/modules/cursor.py
nsz/dist/__init__/kivy_install/modules/inspector.py
nsz/dist/__init__/kivy_install/modules/joycursor.py
nsz/dist/__init__/kivy_install/modules/keybinding.py
nsz/dist/__init__/kivy_install/modules/monitor.py
nsz/dist/__init__/kivy_install/modules/recorder.py
nsz/dist/__init__/kivy_install/modules/screen.py
nsz/dist/__init__/kivy_install/modules/showborder.py
nsz/dist/__init__/kivy_install/modules/touchring.py
nsz/dist/__init__/kivy_install/modules/webdebugger.py
nsz/gui/AboutDialog.py
nsz/gui/DraggableScrollbar.py
nsz/gui/FileDialogs.py
nsz/gui/GameList.py
nsz/gui/GuiPath.py
nsz/gui/Hyperlink.py
nsz/gui/KivyOnTop.py
nsz/gui/NSZ_GUI.py
nsz/gui/RootWidget.py
nsz/gui/SettingScrollOptions.py
nsz/gui/ShaderWidget.py
nsz/gui/fonts/MPLUS1p-Medium.ttf
nsz-4.6.1.dist-info/LICENSE
nsz-4.6.1.dist-info/METADATA
nsz-4.6.1.dist-info/WHEEL
nsz-4.6.1.dist-info/entry_points.txt
nsz-4.6.1.dist-info/top_level.txt
nsz-4.6.1.dist-info/RECORD
