Metadata-Version: 2.1
Name: nsz
Version: 4.6.1
Summary: NSZ - Homebrew compatible NSP/XCI compressor/decompressor
Home-page: https://github.com/nicoboss/nsz
Author: Nico Bosshard
Author-email: nico@bosshome.ch
Maintainer: Nico Bosshard
Maintainer-email: nico@bosshome.ch
Keywords: nsz,xcz,ncz,nsp,xci,nca,Switch
Classifier: Programming Language :: Python :: 3
Classifier: License :: OSI Approved :: MIT License
Classifier: Operating System :: OS Independent
Requires-Python: >=3.6
License-File: LICENSE
Requires-Dist: pycryptodome
Requires-Dist: zstandard
Requires-Dist: enlighten
Provides-Extra: gui
Requires-Dist: kivy ; extra == 'gui'
Requires-Dist: pywin32 ; (platform_system == "Windows") and extra == 'gui'
Requires-Dist: pypiwin32 ; (platform_system == "Windows") and extra == 'gui'
